Workbook

Sheet Introduction
A2: Introduction
A4: This Excel document shows calculations for heat reuse scenarios.
A5: Large offtakers in the F&B sector often operate at approximately 8 MW.
A6: Hence, that range is what these figures are adapted to.
A8: It should be noted that there is a major scaling factor in heat reuse, for piping, but also for offtaker's configuration and OPEX costs.
A9: In other words, should even bigger offtaker needs be identified, then that would decrease costs per MW.
A10: Also note that power costs vary substantially, so they need to be checked when estimating true project costs.
A12: For the identified use cases, the figures used are found in the table below. Greyed out cells are not used in the calculations.
A13: On the next tab, those numbers are used for the calculations, and a dropdown menu (at cell H1) automatically inserts the values from the tables.
A15: The third tab shows the estimated gains for the DC heat exchange room.
A16: The costs and gains are made up of avoided infrastructure, new needed infrastructure, fuel cost avoidance, and governmental incentives.
A17: The client pointed out that in many cases, there is already cooling infrastructure in place, so in those cases, "avoidance" would be zero.
... A28: Petter Terenius for DGA, August 2025
A31: Location | B31: F&B Facility Type | C31: Distance (m) | D31: 1 MWh Electricity (€) | F31: 1 MWh Natural gas (€) | H31: Carbon Tax per MWh (€) | I31: Carbon Tax/Subsidy Comment | J31: Total Carbon Cost | K31: CAPEX Subsidies / Green Financing | L31: CAPEX Subsidies / Green Financing Comment | M31: OPEX subsidy / ton avoided carbon (€) | N31: OPEX subsidy… Comment | O31: DC Temp (°C) | P31: Offtaker Temp (°C) | Q31: Heat need Total / Heat need DC (MW) | R31: Payback period comment
A32: European average | B32: F&B industry | C32: 1000 | D32: 150 | E32: Electricity prices vary widely: must be investigated by actual case. | F32: 54 | G32: Cheaper per MWh, but carbon taxes and volatility make it less attractive. | H32: 12 | I32: EU ETS only applies to industries over 20 MW; thus it does not pertain to the use cases. | J32: =SUM(F32+H32) -> 66 | K32: 0.3 | L32: CAPEX subsidies are often generous, especially for replacing fossil systems w/ heat pumps. | N32: OPEX support is not formalized. EU ETS does not apply. | O32: 30 | P32: 80 | Q32: 8.0/5.6
A33: Germany (Frankfurt) | B33: Meat processing | C33: 1560 | D33: 50 | E33: 180 according to Eurostat, but a scheme is currently running (for five years only) | F33: 58 | G33: Prices in this column (excl UK) are from Eurostat, autumn 2024 | H33: 13 | I33: Prices in this column (excl UK) are from Eurostat, autumn 2024 | J33: =SUM(F33+H33) -> 71 | K33: 0.02 | L33: Max 21,000 euros per heat pump. | M33: 0 | O33: 30 | P33: 80 | Q33: 8.0/5.6
A34: UK/England (Newport) | B34: Processed food | C34: 15000 | D34: 140 | E34: As opposed to typical 215; classified as energy-intensive industries (EII) | F34: 78 | H34: 0 | I34: Carbon tax applies mainly to electricity generators | J34: =SUM(F34+H34) -> 78 | K34: 0.003 | L34: Limited. There is a £7,500 guaranteed grant per heat pump. | M34: 0 | N34: Other scheme: Climate Change Agreements (CCA) | O34: 55 (mix) | P34: 55 | Q34: 8.0/5.6
A35: The Netherlands (Agriport A7) | B35: Horticulture | C35: 1000 | D35: 100 | E35: As opposed to Eurostat's 117, for large industries | F35: 42 | H35: 20 | J35: =SUM(F35+H35) -> 62 | K35: 0.3 | L35: ISDE subsidy. | M35: 0 | O35: 55 | P35: 55 | Q35: 8.0/5.6 | R35: Proposed solution does not need heat pumps. The calculation is not supported properly.
A36: Spain (Zaragoza) | B36: Beer | C36: 3000 | D36: 90 | E36: As opposed to Eurostat's 98, for large industries | F36: 48 | H36: 4 | J36: =SUM(F36+H36) -> 52 | K36: 0.5 | L36: Funded via IDAE. Here: 35% for heat pump and another 15% for installation. | M36: 0 | N36: More schemes: The Interruptibility program; The Capacity market program | O36: 30 | P36: 80 | Q36: 8.0/5.6
A37: Sweden (Staffanstorp) | B37: Oat milk production | C37: 30000 | D37: 90 | E37: In Sweden’s SE4 bidding zone. Reasonable for a large industry (100 in Eurostat) | F37: 78 | H37: 31 | J37: =SUM(F37+H37) -> 109 | K37: 0.25 | L37: No fixed amount. Swedish Energy Agency grants, EU funding mechanisms | M37: 0 | O37: 30 | P37: 75 | Q37: 8.0/5.6 | R37: Sweden has no gas-powered industries, so the calculation is not supported properly.
A38: Natural gas costs are based on many sources, including:
A39: https://tradingeconomics.com/commodity/eu-natural-gas
A40: https://www.iea.org/reports/gas-market-report-q3-2025/executive-summary
A41: https://ec.europa.eu/eurostat/statistics-explained/images/d/d6/Statistic_Explained_figures_for_Gas_2024S2_v2.xlsx

Sheet Offtaker and Piping
F1: European average | I1: Click yellow field to view dropdown list
I2: =_xlfn.XLOOKUP(F1, Introduction!A:A, Introduction!R:R, 0)
A3: Offtaker System and Piping
A4: The system on this tab excludes DC costs (infrastructure) and savings (cooling) | F4: Distance (m) DC to Offtaker | H4: =_xlfn.XLOOKUP(F1, Introduction!A:A, Introduction!C:C, 0) -> 1000 | T4: This is NOT used in the calculation; just included for reference
A5: Delta-T is 12°C on the DC side. | F5: Distance in feet | H5: =SUM(H4*3.281) -> 3281 | I5: Note that changes to the values below
A6: Offtaker power need is 8 MW. Power from DC is 5.6 MW. | I6: will invalidate further dropdown changes. | T6: Temperature Loss Over Distance
A7: Assumes 8760 hour operation. | F7: Electricity price per MWh (€) | H7: =_xlfn.XLOOKUP(F1, Introduction!A:A, Introduction!D:D, 0) -> 150 | T7: Outgoing water temperature (30°C) from DC | W7: 30
F8: Natural gas price per MWh (€) | H8: =_xlfn.XLOOKUP(F1, Introduction!A:A, Introduction!F:F, 0) -> 54 | T8: Ambient temperature (typically 6-10 °C) | W8: 6
A9: Petter Terenius for DGA, July-August 2025 | F9: Carbon tax per MWh (€) | H9: =_xlfn.XLOOKUP(F1, Introduction!A:A, Introduction!H:H, 0) -> 12 | I9: =_xlfn.XLOOKUP(F1, Introduction!A:A, Introduction!I:I, 0) -> EU ETS only applies to industries over 20 MW; thus it does not pertain to the use cases. | T9: Heat loss (°C) | W9: =SUM(U25) -> 0.053543179
F10: CAPEX subsidy (%) | H10: =_xlfn.XLOOKUP(F1, Introduction!A:A, Introduction!K:K, 0) -> 0.3 | I10: =_xlfn.XLOOKUP(F1, Introduction!A:A, Introduction!L:L, 0) -> CAPEX subsidies are often generous, especially for replacing fossil systems w/ heat pumps.
F11: OPEX subsidy per ton avoided c. (€) | H11: =_xlfn.XLOOKUP(F1, Introduction!A:A, Introduction!M:M, 0) -> 0 | I11: =_xlfn.XLOOKUP(F1, Introduction!A:A, Introduction!N:N, 0) -> OPEX support is not formalized. EU ETS does not apply.
T12: Remaining heat (°C) | W12: =SUM(U26) -> 29.946457
A13: 30°C (86°F) scenario | F13: 65°C (150°F) scenario
A14: Water leaves DC at 30°C and returns at 18°C | F14: Water leaves DC at 65°C and returns at 53°C
A16: PIPING CAPEX | F16: PIPING CAPEX | K16: Comments | S16: Piping Heat Loss Calculator
A17: Cost Component | C17: Cost/Meter | D17: Estimated Cost (€) | F17: Cost Component | H17: Cost/Meter | I17: Estimated Cost (€) | S17: Water temperature from DC | U17: =SUM(W7) -> 30
A18: Insulated pipe (forward), 250 mm | C18: 120 | D18: =SUM(C18)*C24 -> 120000 | F18: Insulated pipe (forward), 250 mm | H18: 120 | I18: =SUM(H18)*H24 -> 120000 | K18: Insulated HDPE (SDR17) pipe forward; uninsulated same-size HDPE pipe return. Velocity rate: 2.3 m/s. | S18: Ambient temperature | U18: =SUM(W8) -> 6 | W18: Likely 6-10 degrees for buried pipe in Europe
A19: Uninsulated pipe (return), 250 mm | C19: 45 | D19: =SUM(C19)*C24 -> 45000 | F19: Uninsulated pipe (return), 250 mm | H19: 45 | I19: =SUM(H19)*H24 -> 45000 | K19: Dimensioning is a factor of heat needs, and affects pipe pricing. | S19: Difference water/ambient temp | U19: =SUM(U17-U18) -> 24 | W19: Pipe inner diameter D=0.1308 m
A20: Valves, fittings, sensors | C20: 10 | D20: =SUM(C20)*C24 -> 10000 | F20: Valves, fittings, sensors | H20: 10 | I20: =SUM(H20)*H24 -> 10000 | K20: Valves, fittings, sensors are €4000 per km | S20: U value for pipe | U20: 0.5 | W20: Insulation value. Varies a lot. U=x W/m²·K | Z20: https://www.isoplus.group/products/product-portfolio/details/product/isoflex-single-pipe/
A21: Installation and trenching | C21: 100 | D21: =SUM(C21)*C24 -> 100000 | F21: Installation | H21: 100 | I21: =SUM(H21)*H24 -> 100000 | K21: Trenching costs are heavily dependent on terrain and on hindering infrastructure. | S21: Qloss (W/m) | U21: =SUM(U20*3.1415*0.1308*U19) -> 4.9308984 | W21: Qloss = U*pi*D*deltaT
A22: Project management and design | C22: 50 | D22: =SUM(C22)*C24 -> 50000 | F22: Project management and design | H22: 50 | I22: =SUM(H22)*H24 -> 50000
A23: Pumps to keep pressure over distances (€5000/10 km) | D23: 5000 | F23: Pumps to keep pressure over distances (€5000 /10 km) | I23: 5000
A24: Distance (m) | C24: =SUM(H4) -> 1000 | F24: Distance (m) | H24: =SUM(H4) -> 1000 | K24: Note that at 65°C, steel pipes may be preferable for endurance. This would increase costs by up to 100%. | S24: Heat loss (°C/m) | U24: =SUM((U21)/(22*4186)) -> 5.3543179e-05 | W24: Flow rate = 22 kg/s
A25: Total | D25: =SUM(D18:D24) -> 330000 | F25: Total | I25: =SUM(I18:I24) -> 330000 | S25: Heat loss for installation (°C) | U25: =SUM(U24*H4) -> 0.053543179 | W25: deltaT = (Qloss)/(flow rate*water specific heat capacity)
S26: Remaining heat (°C) | U26: =SUM(U17-U25) -> 29.946457
A29: HEAT PUMP CAPEX per unit | F29: HEAT PUMP CAPEX
A30: Cost Component | C30: % of HP Cost | D30: Estimated Cost (€) | F30: Cost Component | H30: % of HP Cost | I30: Estimated Cost (€)
A31: 8 MW Heat Pump Unit | C31: n/a | D31: 2500000 | F31: 8 MW High-Temp Heat Pump Unit | H31: n/a | I31: 2500000 | K31: Instead of one 8 MW heat pump, it may be advisable to install 2*4 MW heat pumps.
A32: System Integration | C32: 0.2 | D32: =SUM(D31*C32) -> 500000 | F32: System Integration | H32: 0.2 | I32: =SUM(I31*H32) -> 500000 | K32: That would allow for partial load operation and for maintenance without full shutdown.
A33: Automation & Controls | C33: 0.2 | D33: =SUM(D31*C33) -> 500000 | F33: Automation & Controls | H33: 0.2 | I33: =SUM(I31*H33) -> 500000 | K33: The associated CAPEX increasee for that scenario is 10-20%.
A34: Refrigerants | C34: 0.05 | D34: =SUM(D31*C34) -> 125000 | F34: Refrigerants | H34: 0.05 | I34: =SUM(I31*H34) -> 125000
A35: Installation & Commissioning | C35: 0.5 | D35: =SUM(D31*C35) -> 1250000 | F35: Installation & Commissioning | H35: 0.5 | I35: =SUM(I31*H35) -> 1250000
A36: Total | D36: =SUM(D31:D35) -> 4875000 | F36: Total | I36: =SUM(I31:I35) -> 4875000
A40: STORAGE TANK CAPEX | F40: STORAGE TANK CAPEX
A41: Cost Component | C41: Notes | D41: Estimated Cost (€) | F41: Cost Component | H41: % of Tank Cost | I41: Estimated Cost (€)
A42: Tank, 100 m3, plus insulation | C42: Gives 30 mins | D42: 130000 | F42: Tank, 100 m3, plus insulation | H42: Gives 30 mins | I42: 130000 | K42: Needed to level out fluctuations due to differences in returning temperature from offtaker's processes.
A43: Controls, sensors, installation | C43: buffer at full heat | D43: 120000 | F43: Controls, sensors, installation | H43: buffer at full heat | I43: 120000
A44: Total | D44: =SUM(D42:D43) -> 250000 | F44: Total | I44: =SUM(I42:I43) -> 250000
A48: HEAT EXCHANGER CAPEX | F48: HEAT EXCHANGERS CAPEX
A49: Cost Component | C49: % of HX Cost | D49: Estimated Cost (€) | F49: Cost Component | H49: % of HX Cost | I49: Estimated Cost (€)
A50: Heat Exchanger Industrial Process | D50: 200000 | F50: Heat Exchanger Industrial Process | I50: 200000
A51: Installation | C51: 0.1 | D51: =SUM(C51*(D50)) -> 20000 | F51: Heat Exchanger Fluctuations | I51: 100000
A52: Total | D52: =SUM(D50:D51) -> 220000 | F52: Installation | H52: 0.1 | I52: {=SUM(H52*(I50:I51))} -> 30000
F53: Total | I53: =SUM(I50:I52) -> 330000
A57: TOTAL SYSTEM CAPEX | F57: TOTAL SYSTEM CAPEX
A58: Cost Component | D58: Estimated Cost (€) | F58: Cost Component | I58: Estimated Cost (€)
A59: Piping and Trenching | D59: =SUM(D25) -> 330000 | F59: Piping and Trenching | I59: =SUM(I25) -> 330000
A60: 2 Heat Pumps | D60: =SUM(2*D36) -> 9750000 | F60: Heat Pump | I60: =SUM(I36) -> 4875000
A61: Storage Tank | D61: =SUM(D44) -> 250000 | F61: Storage Tank | I61: =SUM(I44) -> 250000
A62: 4 Heat Exchangers (possibly 1 chiller) | D62: =SUM(4*D52) -> 880000 | F62: 2 Heat Exchangers | I62: =SUM(I53) -> 330000
A63: Total | D63: =SUM(D59:D62) -> 11210000 | F63: Total | I63: =SUM(I59:I62) -> 5785000
A67: PIPING OPEX | F67: PIPING OPEX
A68: Cost Component | C68: Cost / Meter | D68: Estimated Cost (€) | F68: Cost Component | H68: Cost / Meter | I68: Estimated Cost (€)
A69: Crude estimate | C69: 45 | D69: =SUM(C69)*C70 -> 45000 | F69: Crude estimate | H69: 45 | I69: =SUM(H69)*H70 -> 45000
A70: Distance (m) | C70: 1000 | F70: Distance (m) | H70: 1000
A71: Total | D71: =SUM(D69:D69) -> 45000 | F71: Total | I71: =SUM(I69:I69) -> 45000
A75: HEAT PUMP OPEX both units | F75: HEAT PUMP OPEX
A76: Cost Component | C76: Notes | D76: Estimated Cost (€) | F76: Cost Component | H76: % of HP Cost | I76: Estimated Cost (€)
A77: Electricity HP A | C77: 1.21 MW added | D77: =SUM((1210*8760*H7/1000)+0) -> 1589940 | F77: Electricity | H77: COP: 7.0 | I77: =SUM(1080*8760*H7/1000) -> 1419120
A78: Electricity HP B | C78: 1.49 MW added | D78: =SUM((1409*8760*H7/1000)+0) -> 1851426 | F78: Maintenance | H78: Temp lift: 12°C | I78: 80000 | K78: Unusually low temperature lift for 65 degree scenario.
A79: Maintenance | D79: 80000 | F79: Monitoring & Control | H79: 1.08 MW added | I79: 20000 | K79: Could be reconfigured in several ways.
A80: Monitoring & Control | D80: 20000 | F80: Insurance & Admin | H80: electricity | I80: 15000
A81: Insurance & Admin | D81: 15000 | F81: Total | I81: =SUM(I77:I80) -> 1534120
A82: Total | D82: =SUM(D77:D81) -> 3556366
A86: STORAGE TANK OPEX | F86: STORAGE TANK OPEX
A87: Cost Component | D87: Estimated Cost (€) | F87: Cost Component | I87: Estimated Cost (€)
A88: Total OPEX | D88: 5000 | F88: Total OPEX | I88: 5000
A89: Total | D89: =SUM(D88:D88) -> 5000 | F89: Total | I89: =SUM(I88:I88) -> 5000
A93: HEAT EXCHANGER OPEX | F93: HEAT EXCHANGER OPEX
A94: Cost Component | D94: Estimated Cost (€) | F94: Cost Component | I94: Estimated Cost (€)
A95: Maintenance | D95: 10000 | F95: Maintenance for both units | I95: 15000
A96: Total | D96: =SUM(D95:D95) -> 10000 | F96: Total | I96: =SUM(I95:I95) -> 15000
A100: TOTAL SYSTEM OPEX | F100: TOTAL SYSTEM OPEX
A101: Cost Component | D101: Estimated Cost (€) | F101: Cost Component | I101: Estimated Cost (€)
A102: Pipe maintenance | D102: =SUM(D71) -> 45000 | F102: Pipe maintenance | I102: =SUM(I71) -> 45000
A103: 2 Heat Pumps, electricity and maintenance | D103: =SUM(D82) -> 3556366 | F103: Heat Pump electricity and maintenance | I103: =SUM(I81) -> 1534120
A104: Storage Tank maintenance | D104: =SUM(D89) -> 5000 | F104: Storage Tank maintenance | I104: =SUM(I89) -> 5000
A105: Heat Exchangers electricity and maintenance | D105: =SUM(D96) -> 10000 | F105: Heat Exchanger electricity and maintenance | I105: =SUM(I96) -> 15000
A106: Total | D106: =SUM(D102:D104) -> 3606366 | F106: Total | I106: =SUM(I102:I104) -> 1584120
A110: PROJECT CASHFLOW: 30°C scenario
A111: Undiscounted and without inflation
C113: Current | D113: Year 1 | E113: Year 2 | F113: Year 3 | G113: Year 4 | H113: Year 5 | I113: Year 6 | J113: Year 7 | K113: Year 8 | L113: Year 9 | M113: Year 10
A114: OPEX | D114: =SUM(D115:D121) -> 776743.45 | E114: =D114 -> 776743.45 | F114: =E114 -> 776743.45 | G114: =F114 -> 776743.45 | H114: =G114 -> 776743.45 | I114: =H114 -> 776743.45 | J114: =I114 -> 776743.45 | K114: =J114 -> 776743.45 | L114: =K114 -> 776743.45 | M114: =L114 -> 776743.45
A115: Piping and Trenching | D115: =-SUM(D71) -> -45000 | E115: =D115 -> -45000 | F115: =E115 -> -45000 | G115: =F115 -> -45000 | H115: =G115 -> -45000 | I115: =H115 -> -45000 | J115: =I115 -> -45000 | K115: =J115 -> -45000 | L115: =K115 -> -45000 | M115: =L115 -> -45000
A116: Heat Pumps maintenance | D116: =-SUM(D79:D81) -> -115000 | E116: =D116 -> -115000 | F116: =E116 -> -115000 | G116: =F116 -> -115000 | H116: =G116 -> -115000 | I116: =H116 -> -115000 | J116: =I116 -> -115000 | K116: =J116 -> -115000 | L116: =K116 -> -115000 | M116: =L116 -> -115000
A117: Storage Tank maintenance | D117: =-SUM(D89) -> -5000 | E117: =D117 -> -5000 | F117: =E117 -> -5000 | G117: =F117 -> -5000 | H117: =G117 -> -5000 | I117: =H117 -> -5000 | J117: =I117 -> -5000 | K117: =J117 -> -5000 | L117: =K117 -> -5000 | M117: =L117 -> -5000
A118: Heat Exchanger maintenance | D118: =-SUM(D95) -> -10000 | E118: =D118 -> -10000 | F118: =E118 -> -10000 | G118: =F118 -> -10000 | H118: =G118 -> -10000 | I118: =H118 -> -10000 | J118: =I118 -> -10000 | K118: =J118 -> -10000 | L118: =K118 -> -10000 | M118: =L118 -> -10000
A119: Electricity for Heat Pumps | D119: =-SUM(D77+D78) -> -3441366 | E119: =D119 -> -3441366 | F119: =E119 -> -3441366 | G119: =F119 -> -3441366 | H119: =G119 -> -3441366 | I119: =H119 -> -3441366 | J119: =I119 -> -3441366 | K119: =J119 -> -3441366 | L119: =K119 -> -3441366 | M119: =L119 -> -3441366
A120: Cost of carbon displaced (1111 kWh per hour and MW) | D120: =SUM(D122*H8) -> 4204379.5 | E120: =D120 -> 4204379.5 | F120: =E120 -> 4204379.5 | G120: =F120 -> 4204379.5 | H120: =G120 -> 4204379.5 | I120: =H120 -> 4204379.5 | J120: =I120 -> 4204379.5 | K120: =J120 -> 4204379.5 | L120: =K120 -> 4204379.5 | M120: =L120 -> 4204379.5
A121: Avoided carbon tax (MWh CO2/year) | D121: =SUM(H9*D123) -> 188729.93 | E121: =D121 -> 188729.93 | F121: =E121 -> 188729.93 | G121: =F121 -> 188729.93 | H121: =G121 -> 188729.93 | I121: =H121 -> 188729.93 | J121: =I121 -> 188729.93 | K121: =J121 -> 188729.93 | L121: =K121 -> 188729.93 | M121: =L121 -> 188729.93
A122: Natural Gas displaced, MWh per year | D122: =SUM(1111*8760*8/1000) -> 77858.88 | E122: =D122 -> 77858.88 | F122: =E122 -> 77858.88 | G122: =F122 -> 77858.88 | H122: =G122 -> 77858.88 | I122: =H122 -> 77858.88 | J122: =I122 -> 77858.88 | K122: =J122 -> 77858.88 | L122: =K122 -> 77858.88 | M122: =L122 -> 77858.88
A123: Natural Gas displaced, Tons CO2 per year | D123: =SUM(D122*0.202) -> 15727.494 | E123: =SUM(E122*0.202) -> 15727.494 | F123: =SUM(F122*0.202) -> 15727.494 | G123: =SUM(G122*0.202) -> 15727.494 | H123: =SUM(H122*0.202) -> 15727.494 | I123: =SUM(I122*0.202) -> 15727.494 | J123: =SUM(J122*0.202) -> 15727.494 | K123: =SUM(K122*0.202) -> 15727.494 | ... M123: =SUM(M122*0.202) -> 15727.494
A124: CAPEX | C124: =SUM(C125:C128) -> -10550000 | D124: 0 | E124: 0 | F124: 0 | G124: 0 | H124: 0 | I124: 0 | J124: 0 | K124: 0 | L124: 0 | M124: 0
A125: Piping and Trenching | C125: =-SUM(D59) -> -330000
A126: Heat Pump(s) | C126: =-SUM(D60) -> -9750000
A127: Storage Tank | C127: =-SUM(D61) -> -250000
A128: Heat Exchangers | C128: =-SUM(D52) -> -220000
A129: Subsidy | C129: =SUM(C130) -> -3165000 | D129: =SUM(D130:D131) -> 0 | E129: =SUM(E130:E131) -> 0 | F129: =SUM(F130:F131) -> 0 | G129: =SUM(G130:G131) -> 0 | H129: =SUM(H130:H131) -> 0 | I129: =SUM(I130:I131) -> 0 | J129: =SUM(J130:J131) -> 0 | K129: =SUM(K130:K131) -> 0 | ... M129: =SUM(M130:M131) -> 0
A130: One-off subsidy | C130: =SUM(C124*H10) -> -3165000
A131: Carbon subsidy | D131: =SUM(H11*D123) -> 0 | E131: =D131 -> 0 | F131: =E131 -> 0 | G131: =F131 -> 0 | H131: =G131 -> 0 | I131: =H131 -> 0 | J131: =I131 -> 0 | K131: =J131 -> 0 | L131: =K131 -> 0 | M131: =L131 -> 0
...

Sheet DC Economics
A2: Data Center Economics
A5: HEAT EXCHANGE ROOM CAPEX
A7: Cost Component | B7: Description | C7: Gain/Cost (€)
A8: HEAT REUSE CASE | C8: =SUM(C9:C20) -> 792000 | D8: Where there is exisiting infrastructure, this is the CAPEX.
A9: Plate heat exchanger | B9: Acts as a thermal bridge, transferring heat between loops | C9: 70000
A10: Primary pumps | B10: Circulate water through the datacenter loop | C10: 40000
A11: Secondary pumps | B11: Circulate water to the recipient loop | C11: 40000
A12: Control valves etc | B12: Regulate flow and temperature | C12: 15000
A13: Temp & flow sensors | B13: Monitor inlet/outlet temperatures and flow rates | C13: 6000
A14: Expansion tank | B14: Manages pressure changes in the closed loop | C14: 8000
A15: Water treatment | B15: Prevents corrosion and scaling in the loop | C15: 10000
A16: Piping | B16: Connects components within the room | C16: 40000
A17: Monitoring system | B17: Controls and monitors system performance | C17: 20000
A18: Safety measures | B18: Racks, mounts, drip trays, leak detection, fire safety | C18: 15000
A19: Redundancy material | B19: 50% of system cost | C19: {=SUM(C9:C18*0.5)} -> 132000
A20: Installation etc | B20: 100% of system cost (including redundancy materials) | C20: {=SUM(C9:C19*1)} -> 396000
A22: HEAT REJECTION CASE | B22: In other words, cost avoidance | C22: =SUM(C23:C29) -> 10450000 | D22: Where there will be no need to build heat rejection infrastructure, use this.
A23: Electric chillers (5.3 MW) | B23: High-efficiency chillers | C23: 3000000 | D23: Be careful with the minus sign, though!
A24: Cooling towers | B24: Rejects heat from condenser water loop | C24: 1500000
A25: Chilled water pumps, piping | B25: Circulates chilled water between chillers and air handlers | C25: 700000
A26: Condenser water pumps | B26: Circulates water between chillers and cooling towers | C26: 400000
A27: Control system | B27: Monitoring and optimization | C27: 350000
A28: Backup power system | B28: UPS + batteries or diesel gensets for cooling continuity | C28: 1500000
A29: Installation etc | B29: Labor, integration, testing | C29: 3000000
A31: Total CAPEX savings | C31: =SUM(C22-C8) -> 9658000 | D31: If no cooling infrastructure exists.
A33: Notes
A34: This calculation shows the difference between cooling and employing heat reuse for 5.6 MW in a data center.
A35: It does not factor in costs which would have been present in both cases, such as air coolers in server rooms.
A39: HEAT EXCHANGE ROOM OPEX COMPARISON
A41: Cost Component | B41: Comment | C41: Gain/Cost (€)
A42: HEAT REUSE CASE | C42: =SUM(C43:C46) -> 220000
A43: Electricity | C43: 120000 | D43: Pumps draw 100 kW.
A44: Maintenance | B44: Simpler components, fewer moving parts | C44: 60000
A45: Chemical treatment | C45: 15000
A46: Monitoring system | B46: Less complex automation in reuse system | C46: 25000 | D46: =SUM(C44:C46) -> 100000 | E46: Total excl power
A48: HEAT REJECTION CASE | B48: In other words, cost avoidance | C48: =SUM(C49:C53) -> 3170000
A49: Electricity | B49: Pumps only in reuse system | C49: 2500000 | D49: Power draw by chillers is approximately 2.0 MW.
A50: Maintenance | C50: 300000 | D50: Fans and pumps add another 350 kW.
A51: Water usage | B51: 70,000 m3 per year | C51: 220000 | D51: Power draw diff (MW): | E51: 2.2
A52: Chemical treatment | B52: Cooling towers require more aggressive treatment | C52: 50000
A53: Monitoring system | C53: 100000
A55: Total savings excluding power | C55: =SUM(D55-D46) -> 570000 | D55: =SUM(C50:C53) -> 670000 | E55: Total excl power
A56: Total OPEX gain | C56: =SUM(C48-C42) -> 2950000
A58: Notes
A59: The huge difference in annual operating cost (more than 90% reduction in heat reuse case) mainly stems from power savings.
A63: INCENTIVE LIST
A64: For a 5.6 MW DC heat reuse scenario (8 MW at offtaker including heat pump)
A66: Country | B66: Incentive | C66: Possible savings (€ M)
A67: GERMANY
B68: CAPEX | C68: =SUM(C69:C71) -> 5360000
B69: Corporate depreciation acceleration | C69: =SUM(2240000) -> 2240000
B70: Regional grant programmes (Land-level) | C70: 1120000
B71: New EU funding (?) | C71: 2000000
B73: OPEX | C73: =SUM(C74) -> 800000
B74: EU ETS (for a 60 MW+ DC) | C74: 800000
A76: UNITED KINGDOM
B77: CAPEX | C77: =SUM(C78:C80) -> 7840000
B78: 100 % Enhanced Capital Allowance | C78: 2800000
B79: Accelerated writing-down on new-build M & E | C79: 1680000
B80: Green Heat Network Fund grant | C80: 3360000
B82: OPEX | C82: =SUM(C83) -> 800000
B83: UK ETS (for a 60 MW+ DC) | C83: 800000
A85: NETHERLANDS
B86: CAPEX | C86: =SUM(C87:C89) -> 7940000
B87: Energy Investment Allowance (EIA) | C87: 2020000
B88: SDE ++ subsidy for recovered heat | C88: 3920000
B89: New EU funding (?) | C89: 2000000
B91: OPEX | C91: =SUM(C92) -> 800000
B92: EU ETS (for a 60 MW+ DC) | C92: 800000
A94: SPAIN
B95: CAPEX | C95: =SUM(C96:C97) -> 4240000
B96: Capital-allowance uplift (pending) | C96: 2240000
B97: New EU funding (?) | C97: 2000000
B99: OPEX | C99: =SUM(C100+C101) -> 900000
B100: VAT reduction on heat sales | C100: 100000
B101: EU ETS (for a 60 MW+ DC) | C101: 800000
A103: SWEDEN
B104: CAPEX | C104: =SUM(C105:C106) -> 2560000
B105: Municipal / EU grant rounds | C105: 560000
B106: New EU funding (?) | C106: 2000000
B108: OPEX | C108: =SUM(C109) -> 800000
B109: EU ETS (for a 60 MW+ DC) | C109: 800000
A112: TOTAL CAPEX SAVINGS ON DC SIDE
A113: Compared with heat rejection through cooling towers
A115: Cost Component | C115: Gain (€)
A116: GERMANY | C116: =SUM(C117:C118) -> 9895600
A117: Cooling - Heat exchange room | C117: =C31 -> 9658000
A118: Incentives estimate, 30% of CAPEX | C118: =SUM(C8*0.3) -> 237600
A120: UNITED KINGDOM | C120: =SUM(C121:C122) -> 9895600
A121: Cooling - Heat exchange room | C121: =C31 -> 9658000
A122: Incentives estimate, 30% of CAPEX | C122: =SUM(C8*0.3) -> 237600
A124: THE NETHERLANDS | C124: =SUM(C125:C126) -> 9895600
A125: Cooling - Heat exchange room | C125: =C31 -> 9658000
A126: Incentives estimate, 30% of CAPEX | C126: =SUM(C8*0.3) -> 237600
A128: SPAIN | C128: =SUM(C129:C130) -> 9895600
A129: Cooling - Heat exchange room | C129: =C31 -> 9658000
A130: Incentives estimate, 30% of CAPEX | C130: =SUM(C8*0.3) -> 237600
A132: SWEDEN | C132: =SUM(C133:C134) -> 9895600
A133: Cooling - Heat exchange room | C133: =C31 -> 9658000
A134: Incentives estimate, 30% of CAPEX | C134: =SUM(C8*0.3) -> 237600
...

Sheet System Flow Diagrams
A2: System Flow Diagrams
